xylosim/v2.so
xylosim/v1.so
xylosim/tools.py
xylosim-0.1.3.dist-info/RECORD
xylosim-0.1.3.dist-info/top_level.txt
xylosim-0.1.3.dist-info/METADATA
xylosim-0.1.3.dist-info/WHEEL
