Metadata-Version: 2.1
Name: xylosim
Version: 0.1.3
Summary: C++ based simulator for quantized spiking neural network accelarators.
Home-page: UNKNOWN
Author: Philipp Weidel
Author-email: philipp.weidel@synsense.ai
License: UNKNOWN
Platform: UNKNOWN
Requires-Dist: pybind11
